pelican/plugins/data_files/__init__.py
pelican/plugins/data_files/file_formats.py
pelican/plugins/data_files/generators.py
pelican/plugins/data_files/tools/__init__.py
pelican/plugins/data_files/tools/cli.py
pelican_data_files-1.1.0.dist-info/LICENSE
pelican_data_files-1.1.0.dist-info/METADATA
pelican_data_files-1.1.0.dist-info/WHEEL
pelican_data_files-1.1.0.dist-info/entry_points.txt
pelican_data_files-1.1.0.dist-info/top_level.txt
pelican_data_files-1.1.0.dist-info/zip-safe
pelican_data_files-1.1.0.dist-info/RECORD
