Metadata-Version: 2.1
Name: pelican-data-files
Version: 1.1.0
Summary: Pelican plugin that allows to load data from files like JSON or YAML.
Home-page: https://github.com/LucasVanHaaren/pelican-data-files
Author: vhash
Author-email: vanhaaren.lucas+dev@gmail.com
License: MIT
Keywords: pelican,pelican-plugin,data
Platform: UNKNOWN
Classifier: Framework :: Pelican :: Plugins
Classifier: Programming Language :: Python :: 3
Classifier: License :: OSI Approved :: MIT License
Requires-Python: >=3.6
Requires-Dist: pelican (>=4.5)
Provides-Extra: dev
Requires-Dist: flake8 ; extra == 'dev'
Requires-Dist: black ; extra == 'dev'
Requires-Dist: invoke ; extra == 'dev'
Requires-Dist: twine ; extra == 'dev'
